4_bit_counter/src/top.v
module top(
	input clk,
	input rst_n,
	output [3:0] led
);

	wire [3:0] count_q;
	wire [3:0] count_d;

	genvar i;
	generate 
		for (i=0;i<4;i=i+1) begin:gen_dff
			d_ff u_dff (
				.clk (clk),
				.rst_n (rst_n),
				.d (count_d[i]),
				.q (count_q[i])
			);
		end
	endgenerate	

	assign led= count_q;
	assign count_d = count_q + 4'd1;
endmodule

module d_ff(
	input clk,
	input rst_n,
	input d,
	output reg q
);

	always @(posedge clk or negedge rst_n) begin
		if (!rst_n)
			q<=1'b0;
		else
			q<=d;
	end
endmodule

4_bit_counter/sim/tb_top.v
`timescale 1ns/1ps

module tb_top;
	reg clk = 0;
	reg rst_n = 0;
	wire [3:0] led;

	always #5 clk=~clk;

	top dut (
		.clk (clk),
		.rst_n (rst_n),
		.led (led)
	);

	initial begin
		$dumpfile( "build/waves.vcd");
		$dumpvars(0,tb_top.clk, tb_top.rst_n, tb_top.led);

		repeat (2) @(posedge clk);
		rst_n=1'b1;
	
		check_value(4'd0,"after reset");

		repeat (5) @(posedge clk);
		check_value(4'd5, "after five increments");

		repeat(10) @(posedge clk);
		check_value(4'd15,"near wrap");

		@(posedge clk);
		check_value(4'd0,"wrap around");

		$display("test pass");
		$finish;
	end

	task check_value(input[3:0] expected, input [63:0] label);
		if (led!== expected) begin
			$fatal(1,"mismatch %0s:expected %0d got %0d at %0t",
				label, expected, led, $time);
			end
	endtask
endmodule

4_bit_counter/build/waves.vcd
$date
	Fri Nov 14 23:08:19 2025
$end
$version
	Icarus Verilog
$end
$timescale
	1ps
$end
$scope module tb_top $end
$var reg 1 ! clk $end
$upscope $end
$scope module tb_top $end
$var reg 1 " rst_n $end
$upscope $end
$scope module tb_top $end
$var wire 4 # led [3:0] $end
$upscope $end
$enddefinitions $end
$comment Show the parameter values. $end
$dumpall
$end
#0
$dumpvars
bx #
0"
0!
$end
#5000
b0 #
1!
#10000
0!
#15000
b1 #
1"
1!
#20000
0!
#25000
b10 #
1!
#30000
0!
#35000
b11 #
1!
#40000
0!
#45000
b100 #
1!
#50000
0!
#55000
b101 #
1!
#60000
0!
#65000
b110 #
1!
#70000
0!
#75000
b111 #
1!
#80000
0!
#85000
b1000 #
1!
#90000
0!
#95000
b1001 #
1!
#100000
0!
#105000
b1010 #
1!
#110000
0!
#115000
b1011 #
1!
#120000
0!
#125000
b1100 #
1!
#130000
0!
#135000
b1101 #
1!
#140000
0!
#145000
b1110 #
1!
#150000
0!
#155000
b1111 #
1!
#160000
0!
#165000
b0 #
1!
#170000
0!
#175000
b1 #
1!
