my_ff/src/top.v
module sr_latch_nand(
	input s_n,
	input r_n,
	output q,
	output q_bar
);
	wire q_int;
	wire q_bar_int;

	nand (q_int, s_n, q_bar_int);
	nand (q_bar_int, r_n, q_int);

	assign q = q_int;
	assign q_bar = q_bar_int;
endmodule

module d_latch_nand(
	input d,
	input enable,
	input reset_n,
	output q,
	output q_bar
);
	wire s_n;
	wire r_n;

	assign s_n = ~(d & enable & reset_n);
	assign r_n = ~( (~d & enable & reset_n) | (~reset_n));

	sr_latch_nand u_latch(
		.s_n(s_n),
		.r_n(r_n),
		.q(q),
		.q_bar(q_bar)
	);
endmodule

module top(
	input clk,
	input reset_n,
	input d,
	output q,
	output q_bar
);
	wire master_q;
	wire master_q_bar;

	d_latch_nand master(
		.d(d),
		.enable(~clk),
		.reset_n(reset_n),
		.q(master_q),
		.q_bar(master_q_bar)
	);

	d_latch_nand slave(
		.d(master_q),
		.enable(clk),
		.reset_n(reset_n),
		.q(q),
		.q_bar(q_bar)
	);
endmodule

my_ff/sim/tb_top.v
`timescale 1ns/1ps

module tb_top;
	reg clk = 0;
	reg reset_n = 0;
	reg d = 0;
	wire q;
	wire q_bar;

	always #5 clk = ~clk;

	top dut(
		.clk(clk),
		.reset_n(reset_n),
		.d(d),
		.q(q),
		.q_bar(q_bar)
	);

	task drive_and_expect(input logic next_d, input int idle_cycles, input int skew_ns);
		begin
			repeat (idle_cycles) @(posedge clk);
			@(negedge clk);
			#(skew_ns);
			d = next_d;
			@(posedge clk);
			#1;
			if (q !== next_d || q_bar !== ~next_d) begin
				$display("Mismatch: d=%0b q=%0b q_bar=%0b", next_d, q, q_bar);
				$fatal;
			end
		end
	endtask

	initial begin
		$dumpfile("build/waves.vcd");
		$dumpvars(0, tb_top.clk, tb_top.reset_n, tb_top.d, tb_top.q, tb_top.q_bar);

		repeat (2) @(posedge clk);
		reset_n = 1;
		@(posedge clk);

		drive_and_expect(1'b1, 0, 1);
		drive_and_expect(1'b0, 1, 2);
		drive_and_expect(1'b1, 0, 4);
		drive_and_expect(1'b0, 2, 1);
		drive_and_expect(1'b1, 1, 3);
		drive_and_expect(1'b0, 0, 0);
		drive_and_expect(1'b1, 3, 2);
		drive_and_expect(1'b0, 0, 4);

		$display("TEST PASS");
		$finish;
	end
endmodule

my_ff/build/waves.vcd
$date
	Tue Nov 11 00:45:11 2025
$end
$version
	Icarus Verilog
$end
$timescale
	1ps
$end
$scope module tb_top $end
$var reg 1 ! clk $end
$upscope $end
$scope module tb_top $end
$var reg 1 " reset_n $end
$upscope $end
$scope module tb_top $end
$var reg 1 # d $end
$upscope $end
$scope module tb_top $end
$var wire 1 $ q $end
$upscope $end
$scope module tb_top $end
$var wire 1 % q_bar $end
$upscope $end
$enddefinitions $end
$comment Show the parameter values. $end
$dumpall
$end
#0
$dumpvars
1%
0$
0#
0"
0!
$end
#5000
1!
#10000
0!
#15000
1"
1!
#20000
0!
#25000
1!
#30000
0!
#31000
1#
#35000
0%
1$
1!
#40000
0!
#45000
1!
#50000
0!
#52000
0#
#55000
0$
1%
1!
#60000
0!
#64000
1#
#65000
0%
1$
1!
#70000
0!
#75000
1!
#80000
0!
#85000
1!
#90000
0!
#91000
0#
#95000
0$
1%
1!
#100000
0!
#105000
1!
#110000
0!
#113000
1#
#115000
0%
1$
1!
#120000
0#
0!
#125000
0$
1%
1!
#130000
0!
#135000
1!
#140000
0!
#145000
1!
#150000
0!
#155000
1!
#160000
0!
#162000
1#
#165000
0%
1$
1!
#170000
0!
#174000
0#
#175000
0$
1%
1!
