D_flip-flop/src/top.v
module top(
	input clock,
	input reset,
	input D,
	output reg Q,
	output Q_not
	);

	always @(posedge clock or posedge reset) begin
		if (reset) begin
			Q <= 1'b0;
		end else begin
			Q <= D;
		end
	end

	assign Q_not = ~Q;
endmodule

D_flip-flop/sim/tb_top.v
`timescale 1ns/1ps
module tb_top;
	reg clock;
	reg reset;
	reg D;
	wire Q;
	wire Q_not;
	

	top dut(
		.clock(clock),
		.reset(reset),
		.D(D),
		.Q(Q),
		.Q_not(Q_not)
		);

		
	always #5 clock=~clock;

	initial begin
		clock =0;
		D=0;
		reset=1;
		#10 reset=0;
		#20 D=1;
		#40 D=0;
		#70 D=1;
		#20 $finish;
	end

	initial begin
		$dumpfile("build/waves.vcd"); 
		$dumpvars(1, tb_top); 
	end

endmodule

D_flip-flop/build/waves.vcd
$date
	Sun Nov  9 19:49:41 2025
$end
$version
	Icarus Verilog
$end
$timescale
	1ps
$end
$scope module tb_top $end
$var wire 1 ! Q_not $end
$var wire 1 " Q $end
$var reg 1 # D $end
$var reg 1 $ clock $end
$var reg 1 % reset $end
$upscope $end
$enddefinitions $end
$comment Show the parameter values. $end
$dumpall
$end
#0
$dumpvars
1%
0$
0#
0"
1!
$end
#5000
1$
#10000
0$
0%
#15000
1$
#20000
0$
#25000
1$
#30000
0$
1#
#35000
0!
1"
1$
#40000
0$
#45000
1$
#50000
0$
#55000
1$
#60000
0$
#65000
1$
#70000
0$
0#
#75000
1!
0"
1$
#80000
0$
#85000
1$
#90000
0$
#95000
1$
#100000
0$
#105000
1$
#110000
0$
#115000
1$
#120000
0$
#125000
1$
#130000
0$
#135000
1$
#140000
0$
1#
#145000
0!
1"
1$
