D_flip-flop/src/top.v
module top(
	input clk,
	input reset,
	input d,
	output reg q,
	output reg q_not
	);



	always @(posedge clk or negedge reset) begin
		if (!reset) begin
			q<= 1'b0;
			q_not <= 1'b1;
		end
		else begin
			q<=d;
			q_not<=~d;
		end
	end 
endmodule

D_flip-flop/sim/tb_top.v
`timescale 1ns/1ps
module tb_top;
	reg clk;
	reg reset;
	reg d;
	wire q;
	wire q_not;

	top dut (
		.clk(clk),
		.reset(reset),
		.d(d),
		.q(q),
		.q_not(q_not)
	);

	initial begin
		clk =0;
		$dumpfile("build/waves.vcd");
		$dumpvars(0, tb_top);
		forever #5 clk = ~clk;
	end

	initial begin 
		reset =0;
		d=0;
		#10 reset=1;
		#20 d=1;
		#20 d=0;
		#20 d=1;
		#100 $finish;
	end

	initial begin
		$monitor("Time=%0t | clk=%b reset=%b d=%b | q=%b q_not=%b", $time,clk, reset, d, q, q_not);
	end
endmodule

D_flip-flop/build/waves.vcd
$date
	Mon Nov  3 22:50:19 2025
$end
$version
	Icarus Verilog
$end
$timescale
	1ps
$end
$scope module tb_top $end
$var wire 1 ! q_not $end
$var wire 1 " q $end
$var reg 1 # clk $end
$var reg 1 $ d $end
$var reg 1 % reset $end
$scope module dut $end
$var wire 1 # clk $end
$var wire 1 $ d $end
$var wire 1 % reset $end
$var reg 1 " q $end
$var reg 1 ! q_not $end
$upscope $end
$upscope $end
$enddefinitions $end
$comment Show the parameter values. $end
$dumpall
$end
#0
$dumpvars
0%
0$
0#
0"
1!
$end
#5000
1#
#10000
0#
1%
#15000
1#
#20000
0#
#25000
1#
#30000
0#
1$
#35000
0!
1"
1#
#40000
0#
#45000
1#
#50000
0#
0$
#55000
1!
0"
1#
#60000
0#
#65000
1#
#70000
0#
1$
#75000
0!
1"
1#
